HTMLReport/__init__.py
HTMLReport/src/__init__.py
HTMLReport/src/test_runner.py
HTMLReport/src/tools/__init__.py
HTMLReport/src/tools/data_driven.py
HTMLReport/src/tools/result.py
HTMLReport/src/tools/retry_on_exception.py
HTMLReport/src/tools/save_images.py
HTMLReport/src/tools/template.py
HTMLReport/src/tools/log/__init__.py
HTMLReport/src/tools/log/handler_factory.py
HTMLReport-2.4.0.dist-info/LICENSE
HTMLReport-2.4.0.dist-info/METADATA
HTMLReport-2.4.0.dist-info/WHEEL
HTMLReport-2.4.0.dist-info/top_level.txt
HTMLReport-2.4.0.dist-info/RECORD
