Metadata-Version: 2.1
Name: HTMLReport
Version: 2.4.0
Summary: Python3 Unittest HTML报告生成器
Home-page: https://github.com/liushilive/htmlreport
Author: 刘士
Author-email: liushilive@outlook.com
License: Apache 2.0
Project-URL: issues, https://github.com/liushilive/htmlreport/issues
Project-URL: The report template, https://liushilive.github.io/report/report/#en
Project-URL: 报告样板, https://liushilive.github.io/report/report/#cn
Project-URL: 个人主页, https://liushilive.github.io/
Keywords: HtmlTestRunner test runner html reports unittest
Classifier: Development Status :: 5 - Production/Stable
Classifier: Intended Audience :: Developers
Classifier: Topic :: Software Development :: Build Tools
Classifier: Topic :: Software Development :: Testing :: Unit
Classifier: Topic :: Software Development :: Libraries :: Python Modules
Classifier: Topic :: Software Development :: User Interfaces
Classifier: License :: OSI Approved :: Apache Software License
Classifier: Natural Language :: Chinese (Simplified)
Classifier: Programming Language :: Python
Classifier: Programming Language :: Python :: 3.7
Classifier: Programming Language :: Python :: 3.8
Classifier: Programming Language :: Python :: Implementation :: CPython
Classifier: Programming Language :: Python :: Implementation :: PyPy
License-File: LICENSE
